example_package/__init__.py
example_package/example.py
juspreet51/__init__.py
juspreet51-0.0.2.dist-info/LICENSE
juspreet51-0.0.2.dist-info/METADATA
juspreet51-0.0.2.dist-info/WHEEL
juspreet51-0.0.2.dist-info/top_level.txt
juspreet51-0.0.2.dist-info/RECORD
