Metadata-Version: 2.1
Name: juspreet51
Version: 0.0.2
Summary: use JusPy instead
Home-page: https://pypi.org/project/juspy/
Author: Jaspreet Singh
License: UNKNOWN
Platform: UNKNOWN
Classifier: Programming Language :: Python :: 3
Classifier: License :: OSI Approved :: MIT License
Classifier: Operating System :: OS Independent
Requires-Python: >=3.6
License-File: LICENSE
